Portkey-0.1.1.dist-info/DESCRIPTION.rst
Portkey-0.1.1.dist-info/METADATA
Portkey-0.1.1.dist-info/RECORD
Portkey-0.1.1.dist-info/WHEEL
Portkey-0.1.1.dist-info/metadata.json
Portkey-0.1.1.dist-info/top_level.txt
portkey/__init__.py
portkey/decorators.py
portkey/portkey.py
portkey/selector.py
portkey/utilities.py
