Metadata-Version: 2.0
Name: Portkey
Version: 0.1.1
Summary: A Python framework for interacting with in-browser DOM via websockets
Home-page: https://github.com/red8012/portkey
Author: Yu-Ann Chen
Author-email: red8012@gmail.com
License: Apache License 2.0
Platform: UNKNOWN
Classifier: Development Status :: 2 - Pre-Alpha
Classifier: Environment :: Web Environment
Classifier: Intended Audience :: Developers
Classifier: Programming Language :: Python :: 3.6
Requires-Dist: websockets (>=3.2)
Requires-Dist: werkzeug (>=0.11)
